gpt_jupyterlab/__init__.py
gpt_jupyterlab/_version.py
gpt_jupyterlab/handlers.py
gpt_jupyterlab/tests/__init__.py
gpt_jupyterlab/tests/test_handlers.py
gpt_jupyterlab-0.1.4.data/data/etc/jupyter/jupyter_notebook_config.d/gpt_jupyterlab.json
gpt_jupyterlab-0.1.4.data/data/etc/jupyter/jupyter_server_config.d/gpt_jupyterlab.json
gpt_jupyterlab-0.1.4.data/data/share/jupyter/labextensions/gpt_jupyterlab/package.json
gpt_jupyterlab-0.1.4.data/data/share/jupyter/labextensions/gpt_jupyterlab/schemas/gpt_jupyterlab/package.json.orig
gpt_jupyterlab-0.1.4.data/data/share/jupyter/labextensions/gpt_jupyterlab/schemas/gpt_jupyterlab/plugin.json
gpt_jupyterlab-0.1.4.data/data/share/jupyter/labextensions/gpt_jupyterlab/static/747.9efb83b48bf8c8de0c74.js
gpt_jupyterlab-0.1.4.data/data/share/jupyter/labextensions/gpt_jupyterlab/static/977.960403d3967b615d6a50.js
gpt_jupyterlab-0.1.4.data/data/share/jupyter/labextensions/gpt_jupyterlab/static/remoteEntry.44a590b38d75ee349393.js
gpt_jupyterlab-0.1.4.data/data/share/jupyter/labextensions/gpt_jupyterlab/static/style.js
gpt_jupyterlab-0.1.4.data/data/share/jupyter/labextensions/gpt_jupyterlab/static/third-party-licenses.json
gpt_jupyterlab-0.1.4.data/data/share/jupyter/labextensions/gpt_jupyterlab/install.json
gpt_jupyterlab-0.1.4.dist-info/METADATA
gpt_jupyterlab-0.1.4.dist-info/WHEEL
gpt_jupyterlab-0.1.4.dist-info/licenses/LICENSE
gpt_jupyterlab-0.1.4.dist-info/RECORD
