Metadata-Version: 2.1
Name: gpt_jupyterlab
Version: 0.1.4
Summary: Use OpenAI GPT models for text and code completion on your notebook cells
Project-URL: Homepage, https://github.com/henshinger/gpt-jupyterlab
Project-URL: Bug Tracker, https://github.com/henshinger/gpt-jupyterlab.git/issues
Project-URL: Repository, https://github.com/henshinger/gpt-jupyterlab.git
Author-email: Kenley Tan <kenley.tan@hey.com>
License: BSD 3-Clause License
License-File: LICENSE
Classifier: Framework :: Jupyter
Classifier: Framework :: Jupyter :: JupyterLab
Classifier: Framework :: Jupyter :: JupyterLab :: 3
Classifier: Framework :: Jupyter :: JupyterLab :: Extensions
Classifier: Framework :: Jupyter :: JupyterLab :: Extensions :: Prebuilt
Classifier: License :: OSI Approved :: BSD License
Classifier: Programming Language :: Python
Classifier: Programming Language :: Python :: 3
Classifier: Programming Language :: Python :: 3.7
Classifier: Programming Language :: Python :: 3.8
Classifier: Programming Language :: Python :: 3.9
Classifier: Programming Language :: Python :: 3.10
Classifier: Programming Language :: Python :: 3.11
Requires-Python: >=3.7
Requires-Dist: jupyter-server<3,>=1.21
Requires-Dist: openai
Requires-Dist: tenacity
Provides-Extra: test
Requires-Dist: coverage; extra == 'test'
Requires-Dist: pytest; extra == 'test'
Requires-Dist: pytest-asyncio; extra == 'test'
Requires-Dist: pytest-cov; extra == 'test'
Requires-Dist: pytest-jupyter[server]>=0.6.0; extra == 'test'
